archive_steam_reviews/__init__.py
archive_steam_reviews/__main__.py
archive_steam_reviews/cli.py
archive_steam_reviews-0.2.1.dist-info/AUTHORS.rst
archive_steam_reviews-0.2.1.dist-info/LICENSE
archive_steam_reviews-0.2.1.dist-info/METADATA
archive_steam_reviews-0.2.1.dist-info/WHEEL
archive_steam_reviews-0.2.1.dist-info/entry_points.txt
archive_steam_reviews-0.2.1.dist-info/top_level.txt
archive_steam_reviews-0.2.1.dist-info/RECORD
